{
  "size": 1586956,
  "nb_rows": 3319,
  "nb_profiled_rows": 2756,
  "nb_columns": 29,
  "columns": [
    {
      "name": "objectid",
      "structural_type": "http://schema.org/Integer",
      "semantic_types": [
        "http://schema.org/identifier"
      ],
      "unclean_values_ratio": 0.0,
      "num_distinct_values": 3319,
      "mean": 11295.58962264151,
      "stddev": 963.417772880883,
      "coverage": [
        {
          "range": {
            "gte": 9656.0,
            "lte": 10689.0
          }
        },
        {
          "range": {
            "gte": 10798.0,
            "lte": 11801.0
          }
        },
        {
          "range": {
            "gte": 11908.0,
            "lte": 12889.0
          }
        }
      ]
    },
    {
      "name": "borough",
      "structural_type": "http://schema.org/Text",
      "semantic_types": [
        "http://schema.org/AdministrativeArea"
      ],
      "geo_classifier": {
        "label": "borough_code",
        "confidence": 0.6277474761009216,
        "source": "ml+validated"
      }
    },
    {
      "name": "type",
      "structural_type": "http://schema.org/Text",
      "semantic_types": [
        "http://schema.org/Enumeration"
      ],
      "num_distinct_values": 3
    },
    {
      "name": "provider",
      "structural_type": "http://schema.org/Text",
      "semantic_types": [
        "http://schema.org/Enumeration"
      ],
      "num_distinct_values": 17
    },
    {
      "name": "name",
      "structural_type": "http://schema.org/Text",
      "semantic_types": [],
      "missing_values_ratio": 0.06567489114658925,
      "num_distinct_values": 2500
    },
    {
      "name": "location",
      "structural_type": "http://schema.org/Text",
      "semantic_types": [
        "http://schema.org/address"
      ],
      "geo_classifier": {
        "label": "address",
        "confidence": 0.9270782470703125,
        "source": "ml"
      }
    },
    {
      "name": "latitude",
      "structural_type": "http://schema.org/Float",
      "semantic_types": [
        "http://schema.org/latitude"
      ],
      "geo_classifier": {
        "label": "latitude",
        "confidence": 0.6101157665252686,
        "source": "ml+validated"
      },
      "mean": 40.741149685615696,
      "stddev": 0.06687348527690343,
      "coverage": [
        {
          "range": {
            "gte": 40.5733840001,
            "lte": 40.6952050001
          }
        },
        {
          "range": {
            "gte": 40.7051723129,
            "lte": 40.7737521088
          }
        },
        {
          "range": {
            "gte": 40.7858130496,
            "lte": 40.866804429
          }
        }
      ]
    },
    {
      "name": "longitude",
      "structural_type": "http://schema.org/Float",
      "semantic_types": [
        "http://schema.org/longitude"
      ],
      "geo_classifier": {
        "label": "longitude",
        "confidence": 0.9536051750183105,
        "source": "ml+validated"
      },
      "mean": -73.95066659705284,
      "stddev": 0.062363450654750005,
      "coverage": [
        {
          "range": {
            "gte": -74.0844060005,
            "lte": -73.9661066097
          }
        },
        {
          "range": {
            "gte": -73.9590295104,
            "lte": -73.8862530003
          }
        },
        {
          "range": {
            "gte": -73.8713797301,
            "lte": -73.7456735613
          }
        }
      ]
    },
    {
      "name": "x",
      "structural_type": "http://schema.org/Float",
      "semantic_types": [],
      "geo_classifier": {
        "label": "x_coord",
        "confidence": 0.6721897721290588,
        "source": "ml+validated"
      },
      "mean": 997916.4719369519,
      "stddev": 17291.13087654464,
      "coverage": [
        {
          "range": {
            "gte": 960801.372673,
            "lte": 993605.441907
          }
        },
        {
          "range": {
            "gte": 995591.686622,
            "lte": 1015771.7775
          }
        },
        {
          "range": {
            "gte": 1019864.59707,
            "lte": 1054846.80138
          }
        }
      ]
    },
    {
      "name": "y",
      "structural_type": "http://schema.org/Float",
      "semantic_types": [],
      "unclean_values_ratio": 0.0,
      "mean": 209307.54968958098,
      "stddev": 24361.886336944204,
      "coverage": [
        {
          "range": {
            "gte": 148176.405469,
            "lte": 192596.114201
          }
        },
        {
          "range": {
            "gte": 196245.014712,
            "lte": 221195.710545
          }
        },
        {
          "range": {
            "gte": 225570.513476,
            "lte": 255107.424218
          }
        }
      ],
      "geo_classifier": {
        "label": "y_coord",
        "confidence": 0.95,
        "source": "wrapper"
      },
      "wrapper_reason": "y_coord_xy_pair"
    },
    {
      "name": "location_t",
      "structural_type": "http://schema.org/Text",
      "semantic_types": [
        "http://schema.org/Enumeration"
      ],
      "num_distinct_values": 16
    },
    {
      "name": "remarks",
      "structural_type": "http://schema.org/Text",
      "semantic_types": [
        "http://schema.org/Text"
      ],
      "missing_values_ratio": 0.15965166908563136
    },
    {
      "name": "city",
      "structural_type": "http://schema.org/Text",
      "semantic_types": [
        "http://schema.org/Enumeration",
        "http://schema.org/AdministrativeArea"
      ],
      "num_distinct_values": 44,
      "geo_classifier": {
        "label": "city",
        "confidence": 0.95,
        "source": "wrapper"
      },
      "wrapper_reason": "city_name_and_values"
    },
    {
      "name": "ssid",
      "structural_type": "http://schema.org/Text",
      "semantic_types": [
        "http://schema.org/Enumeration"
      ],
      "num_distinct_values": 16
    },
    {
      "name": "sourceid",
      "structural_type": "http://schema.org/Text",
      "semantic_types": [],
      "missing_values_ratio": 0.3167634252539913,
      "num_distinct_values": 1872
    },
    {
      "name": "activated",
      "structural_type": "http://schema.org/Text",
      "semantic_types": [
        "http://schema.org/DateTime"
      ],
      "num_distinct_values": 416
    },
    {
      "name": "borocode",
      "structural_type": "http://schema.org/Text",
      "semantic_types": [
        "http://schema.org/AdministrativeArea"
      ],
      "geo_classifier": {
        "label": "borough_code",
        "confidence": 0.7853758335113525,
        "source": "ml+validated"
      }
    },
    {
      "name": "boroname",
      "structural_type": "http://schema.org/Text",
      "semantic_types": [
        "http://schema.org/Enumeration",
        "http://schema.org/AdministrativeArea"
      ],
      "num_distinct_values": 5,
      "geo_classifier": {
        "label": "borough_code",
        "confidence": 0.95,
        "source": "wrapper"
      },
      "wrapper_reason": "admin_name_and_values"
    },
    {
      "name": "ntacode",
      "structural_type": "http://schema.org/Text",
      "semantic_types": [
        "http://schema.org/Enumeration",
        "http://schema.org/AdministrativeArea"
      ],
      "num_distinct_values": 178,
      "geo_classifier": {
        "label": "borough_code",
        "confidence": 0.95,
        "source": "wrapper"
      },
      "wrapper_reason": "admin_name_and_values"
    },
    {
      "name": "ntaname",
      "structural_type": "http://schema.org/Text",
      "semantic_types": [
        "http://schema.org/Enumeration",
        "http://schema.org/AdministrativeArea"
      ],
      "num_distinct_values": 179,
      "geo_classifier": {
        "label": "borough_code",
        "confidence": 0.95,
        "source": "wrapper"
      },
      "wrapper_reason": "admin_name_and_values"
    },
    {
      "name": "coundist",
      "structural_type": "http://schema.org/Text",
      "semantic_types": [
        "http://schema.org/AdministrativeArea"
      ],
      "unclean_values_ratio": 0.0,
      "num_distinct_values": 51,
      "mean": 17.2666908563135,
      "stddev": 14.936549184179917,
      "coverage": [
        {
          "range": {
            "gte": 1.0,
            "lte": 10.0
          }
        },
        {
          "range": {
            "gte": 14.0,
            "lte": 29.0
          }
        },
        {
          "range": {
            "gte": 32.0,
            "lte": 50.0
          }
        }
      ],
      "geo_classifier": {
        "label": "borough_code",
        "confidence": 0.95,
        "source": "wrapper"
      },
      "wrapper_reason": "admin_name_and_values"
    },
    {
      "name": "zip",
      "structural_type": "http://schema.org/Text",
      "semantic_types": [
        "http://schema.org/address"
      ],
      "unclean_values_ratio": 0.0,
      "num_distinct_values": 172,
      "mean": 10534.21915820029,
      "stddev": 583.1660352624812,
      "coverage": [
        {
          "range": {
            "gte": 10002.0,
            "lte": 10039.0
          }
        },
        {
          "range": {
            "gte": 10304.0,
            "lte": 10468.0
          }
        },
        {
          "range": {
            "gte": 11101.0,
            "lte": 11434.0
          }
        }
      ],
      "geo_classifier": {
        "label": "zip5",
        "confidence": 0.99,
        "source": "wrapper"
      },
      "wrapper_reason": "zip_name_and_pattern"
    },
    {
      "name": "borocd",
      "structural_type": "http://schema.org/Text",
      "semantic_types": [
        "http://schema.org/AdministrativeArea"
      ],
      "unclean_values_ratio": 0.0,
      "num_distinct_values": 67,
      "mean": 219.0134252539913,
      "stddev": 128.4077132465721,
      "coverage": [
        {
          "range": {
            "gte": 101.0,
            "lte": 207.0
          }
        },
        {
          "range": {
            "gte": 301.0,
            "lte": 412.0
          }
        }
      ],
      "geo_classifier": {
        "label": "borough_code",
        "confidence": 0.95,
        "source": "wrapper"
      },
      "wrapper_reason": "admin_name_and_values"
    },
    {
      "name": "ct2010",
      "structural_type": "http://schema.org/Integer",
      "semantic_types": [],
      "unclean_values_ratio": 0.0,
      "num_distinct_values": 552,
      "mean": 2483.6473149492017,
      "stddev": 12972.364089426668,
      "coverage": [
        {
          "range": {
            "gte": 13.0,
            "lte": 837.0
          }
        }
      ]
    },
    {
      "name": "bctcb2010",
      "structural_type": "http://schema.org/Integer",
      "semantic_types": [],
      "unclean_values_ratio": 0.0,
      "num_distinct_values": 552,
      "mean": 2483.6473149492017,
      "stddev": 12972.364089426668,
      "coverage": [
        {
          "range": {
            "gte": 13.0,
            "lte": 837.0
          }
        }
      ]
    },
    {
      "name": "bin",
      "structural_type": "http://schema.org/Integer",
      "semantic_types": [],
      "unclean_values_ratio": 0.0,
      "num_distinct_values": 2107,
      "mean": 1583847.970609579,
      "stddev": 1459298.473833369,
      "coverage": [
        {
          "range": {
            "gte": 0.0,
            "lte": 0.0
          }
        },
        {
          "range": {
            "gte": 1006096.0,
            "lte": 2013738.0
          }
        },
        {
          "range": {
            "gte": 3000461.0,
            "lte": 5051531.0
          }
        }
      ]
    },
    {
      "name": "bbl",
      "structural_type": "http://schema.org/Integer",
      "semantic_types": [],
      "unclean_values_ratio": 0.0,
      "num_distinct_values": 2119,
      "mean": 1748727644.1153846,
      "stddev": 1417696542.9852498,
      "coverage": [
        {
          "range": {
            "gte": 0.0,
            "lte": 0.0
          }
        },
        {
          "range": {
            "gte": 1001110160.0,
            "lte": 2031550001.0
          }
        },
        {
          "range": {
            "gte": 3001510027.0,
            "lte": 5035250200.0
          }
        }
      ]
    },
    {
      "name": "doitt_id",
      "structural_type": "http://schema.org/Integer",
      "semantic_types": [
        "http://schema.org/identifier"
      ],
      "unclean_values_ratio": 0.0,
      "num_distinct_values": 3319,
      "mean": 2691.523947750363,
      "stddev": 1594.5384991239546,
      "coverage": [
        {
          "range": {
            "gte": 67.0,
            "lte": 1709.0
          }
        },
        {
          "range": {
            "gte": 3060.0,
            "lte": 3926.0
          }
        },
        {
          "range": {
            "gte": 4014.0,
            "lte": 4900.0
          }
        }
      ]
    },
    {
      "name": "location_lat_long",
      "structural_type": "http://schema.org/Text",
      "semantic_types": [],
      "mean": 0,
      "stddev": 0,
      "wrapper_reason": "clear_scalar_coord_on_pair_text"
    }
  ],
  "nb_spatial_columns": 5,
  "nb_temporal_columns": 1,
  "nb_categorical_columns": 8,
  "nb_numerical_columns": 12,
  "types": [
    "categorical",
    "numerical",
    "spatial",
    "temporal"
  ],
  "spatial_coverage": [
    {
      "type": "latlong",
      "column_names": [
        "latitude",
        "longitude"
      ],
      "column_indexes": [
        6,
        7
      ],
      "geohashes4": [
        {
          "hash": "1211303202202",
          "number": 71
        },
        {
          "hash": "1211303202203",
          "number": 222
        },
        {
          "hash": "1211303202200",
          "number": 130
        },
        {
          "hash": "1211303202201",
          "number": 16
        },
        {
          "hash": "1211303202231",
          "number": 56
        },
        {
          "hash": "1211303202233",
          "number": 4
        },
        {
          "hash": "1211303202230",
          "number": 44
        },
        {
          "hash": "1211303202232",
          "number": 6
        },
        {
          "hash": "1211303202221",
          "number": 33
        },
        {
          "hash": "1211303202223",
          "number": 4
        },
        {
          "hash": "1211303202222",
          "number": 1
        },
        {
          "hash": "1211303202212",
          "number": 93
        },
        {
          "hash": "1211303202213",
          "number": 31
        },
        {
          "hash": "1211303202320",
          "number": 12
        },
        {
          "hash": "1211303202323",
          "number": 1
        },
        {
          "hash": "1211303202322",
          "number": 13
        },
        {
          "hash": "1211303202321",
          "number": 2
        },
        {
          "hash": "1211303220011",
          "number": 6
        },
        {
          "hash": "1211303220010",
          "number": 4
        },
        {
          "hash": "1211303220001",
          "number": 5
        },
        {
          "hash": "1211303220002",
          "number": 1
        },
        {
          "hash": "1211302313311",
          "number": 201
        },
        {
          "hash": "1211302313312",
          "number": 72
        },
        {
          "hash": "1211302313310",
          "number": 359
        },
        {
          "hash": "1211302313313",
          "number": 80
        },
        {
          "hash": "1211302313303",
          "number": 22
        },
        {
          "hash": "1211302313300",
          "number": 86
        },
        {
          "hash": "1211302313301",
          "number": 144
        },
        {
          "hash": "1211302313302",
          "number": 45
        },
        {
          "hash": "1211302313323",
          "number": 36
        },
        {
          "hash": "1211302313321",
          "number": 20
        },
        {
          "hash": "1211302313322",
          "number": 33
        },
        {
          "hash": "1211302313320",
          "number": 5
        },
        {
          "hash": "1211302313330",
          "number": 60
        },
        {
          "hash": "1211302313331",
          "number": 7
        },
        {
          "hash": "1211302313332",
          "number": 11
        },
        {
          "hash": "1211302313233",
          "number": 17
        },
        {
          "hash": "1211302313230",
          "number": 15
        },
        {
          "hash": "1211302313231",
          "number": 24
        },
        {
          "hash": "1211302313232",
          "number": 1
        },
        {
          "hash": "1211302313213",
          "number": 51
        },
        {
          "hash": "1211302313210",
          "number": 44
        },
        {
          "hash": "1211302313211",
          "number": 147
        },
        {
          "hash": "1211302313212",
          "number": 39
        },
        {
          "hash": "1211302313200",
          "number": 8
        },
        {
          "hash": "1211302313203",
          "number": 14
        },
        {
          "hash": "1211302313201",
          "number": 6
        },
        {
          "hash": "1211302313202",
          "number": 3
        },
        {
          "hash": "1211302313221",
          "number": 2
        },
        {
          "hash": "1211302313132",
          "number": 27
        },
        {
          "hash": "1211302313122",
          "number": 48
        },
        {
          "hash": "1211302313123",
          "number": 30
        },
        {
          "hash": "1211302313033",
          "number": 37
        },
        {
          "hash": "1211302313032",
          "number": 4
        },
        {
          "hash": "1211302313023",
          "number": 7
        },
        {
          "hash": "1211302313020",
          "number": 3
        },
        {
          "hash": "1211302313022",
          "number": 8
        },
        {
          "hash": "1211302313021",
          "number": 1
        },
        {
          "hash": "1211302313003",
          "number": 13
        },
        {
          "hash": "1211302313002",
          "number": 9
        },
        {
          "hash": "1211302313000",
          "number": 1
        },
        {
          "hash": "1211302312310",
          "number": 29
        },
        {
          "hash": "1211302312313",
          "number": 5
        },
        {
          "hash": "1211302312311",
          "number": 7
        },
        {
          "hash": "1211302312312",
          "number": 13
        },
        {
          "hash": "1211302312332",
          "number": 5
        },
        {
          "hash": "1211302312113",
          "number": 6
        },
        {
          "hash": "1211302312112",
          "number": 23
        },
        {
          "hash": "1211302312110",
          "number": 1
        },
        {
          "hash": "1211302312111",
          "number": 4
        },
        {
          "hash": "1211302312130",
          "number": 13
        },
        {
          "hash": "1211302312131",
          "number": 6
        },
        {
          "hash": "1211302312101",
          "number": 1
        },
        {
          "hash": "1211302310233",
          "number": 2
        },
        {
          "hash": "1211302310231",
          "number": 1
        },
        {
          "hash": "1211302310322",
          "number": 3
        },
        {
          "hash": "1211302331011",
          "number": 13
        },
        {
          "hash": "1211302331013",
          "number": 20
        },
        {
          "hash": "1211302331010",
          "number": 2
        },
        {
          "hash": "1211302331030",
          "number": 1
        },
        {
          "hash": "1211302331100",
          "number": 33
        },
        {
          "hash": "1211302331103",
          "number": 8
        },
        {
          "hash": "1211302331101",
          "number": 2
        },
        {
          "hash": "1211302331102",
          "number": 4
        },
        {
          "hash": "1211302331111",
          "number": 6
        },
        {
          "hash": "1211302331112",
          "number": 1
        },
        {
          "hash": "1211302331110",
          "number": 15
        },
        {
          "hash": "1211302331113",
          "number": 1
        },
        {
          "hash": "1211302331130",
          "number": 8
        },
        {
          "hash": "1211302331131",
          "number": 1
        },
        {
          "hash": "1211302331121",
          "number": 2
        },
        {
          "hash": "1211302331120",
          "number": 1
        },
        {
          "hash": "1211302330113",
          "number": 11
        },
        {
          "hash": "1211302330110",
          "number": 5
        },
        {
          "hash": "1211302330111",
          "number": 8
        }
      ],
      "ranges": [
        {
          "range": {
            "type": "envelope",
            "coordinates": [
              [
                -74.1016290006,
                40.7466513201
              ],
              [
                -73.9422392381,
                40.5760999997
              ]
            ]
          }
        },
        {
          "range": {
            "type": "envelope",
            "coordinates": [
              [
                -73.984569,
                40.8606299996
              ],
              [
                -73.8930594396,
                40.7493411197
              ]
            ]
          }
        },
        {
          "range": {
            "type": "envelope",
            "coordinates": [
              [
                -73.9029900497,
                40.7601255812
              ],
              [
                -73.7462619996,
                40.593146783
              ]
            ]
          }
        }
      ],
      "number": 2756
    }
  ],
  "temporal_coverage": [
    {
      "type": "datetime",
      "column_names": [
        "activated"
      ],
      "column_indexes": [
        15
      ],
      "column_types": [
        "http://schema.org/DateTime"
      ],
      "ranges": [
        {
          "range": {
            "gte": 1475193600.0,
            "lte": 1531958400.0
          }
        },
        {
          "range": {
            "gte": 253392453632.0,
            "lte": 253392453632.0
          }
        }
      ],
      "temporal_resolution": "day"
    }
  ],
  "attribute_keywords": [
    "objectid",
    "borough",
    "type",
    "provider",
    "name",
    "location",
    "latitude",
    "longitude",
    "x",
    "y",
    "location_t",
    "location",
    "t",
    "remarks",
    "city",
    "ssid",
    "sourceid",
    "activated",
    "borocode",
    "boroname",
    "ntacode",
    "ntaname",
    "coundist",
    "zip",
    "borocd",
    "ct2010",
    "ct",
    "2010",
    "bctcb2010",
    "bctcb",
    "2010",
    "bin",
    "bbl",
    "doitt_id",
    "doitt",
    "id",
    "location_lat_long",
    "location",
    "lat",
    "long"
  ],
  "sample": "objectid,borough,type,provider,name,location,latitude,longitude,x,y,location_t,remarks,city,ssid,sourceid,activated,borocode,boroname,ntacode,ntaname,coundist,zip,borocd,ct2010,bctcb2010,bin,bbl,doitt_id,location_lat_long\r\n9760,4,Free,LinkNYC - Citybridge,qu-02-125075,51-30 NORTHERN BOULEVARD,40.75313916990,-73.90745354010,1009890.90015000000,213679.13240300000,Outdoor Kiosk,\"Tablet Internet -phone , Free 1 GB Wi-FI Service\",Queens,LinkNYC Free Wi-Fi,LINK-011268,2018-06-20T00:00:00.000,4,Queens,QN63,Woodside,26.00000000000,11377,402.00000000000,255.00000000000,255.00000000000,4437089.00000000000,4011920040.00000000000,4877,\"(40.7531391699, -73.9074535401)\"\r\n12382,3,Free,Transit Wireless,Clinton-Washington Avs (C),Clinton-Washington Avs (C),40.68326300000,-73.96583799980,993724.84554000000,188209.40611100000,Subway Station,SN 177,Brooklyn,TransitWirelessWiFi,,9999-09-09T00:00:00.000,3,Brooklyn,BK69,Clinton Hill,35.00000000000,11238,302.00000000000,199.00000000000,199.00000000000,0.00000000000,0.00000000000,1711,\"(40.683263, -73.9658379998)\"\r\n10274,4,Free,LinkNYC - Citybridge,qu-01-145947,34-24 30 AVENUE,40.76540164980,-73.91836040980,1006864.88258000000,218143.74847400000,Outdoor Kiosk,\"Tablet Internet -phone , Free 1 GB Wi-FI Service\",Queens,LinkNYC Free Wi-Fi,LINK-021330,2017-10-25T00:00:00.000,4,Queens,QN70,Astoria,22.00000000000,11103,401.00000000000,63.00000000000,63.00000000000,4009091.00000000000,4006260050.00000000000,4679,\"(40.7654016498, -73.9183604098)\"\r\n11755,1,Free,LinkNYC - Citybridge,mn-09-134415,2848 BROADWAY,40.80439875000,-73.96632817040,993571.93180400000,232342.97565200000,Outdoor Kiosk,\"Tablet Internet -phone , Free 1 GB Wi-FI Service\",New York,LinkNYC Free Wi-Fi,LINK-011088,2018-01-12T00:00:00.000,1,Manhattan,MN09,Morningside Heights,7.00000000000,10025,109.00000000000,199.00000000000,199.00000000000,1056917.00000000000,1018820060.00000000000,3991,\"(40.80439875, -73.9663281704)\"\r\n9940,4,Free,QPL,Kew Gardens Hills,72-33 VLEIGH PLACE,40.72591848560,-73.82071906960,1033941.80382000000,203799.08096900000,Library,,Flushing,QBPL_WIRELESS,,9999-09-09T00:00:00.000,4,Queens,QN37,Kew Gardens Hills,24.00000000000,11367,408.00000000000,77907.00000000000,77907.00000000000,4144059.00000000000,4066610005.00000000000,354,\"(40.7259184856, -73.8207190696)\"\r\n12222,1,Free,LinkNYC - Citybridge,mn-06-136202,160 East 38Th Street,40.74828704370,-73.97653467960,990751.77077700000,211898.67238100000,Outdoor Kiosk,\"Tablet Internet -phone , Free 1 GB Wi-FI Service\",New York,LinkNYC Free Wi-Fi,LINK-000233,2016-03-18T00:00:00.000,1,Manhattan,MN20,Murray Hill-Kips Bay,4.00000000000,10016,106.00000000000,80.00000000000,80.00000000000,1019099.00000000000,1008930040.00000000000,3105,\"(40.7482870437, -73.9765346796)\"\r\n11254,4,Free,LinkNYC - Citybridge,qu-03-100928,80-05 ROOSEVELT AVENUE,40.74753882010,-73.88549761020,1015976.66882000000,211645.93535400000,Outdoor Kiosk,\"Tablet Internet -phone , Free 1 GB Wi-FI Service\",Queens,LinkNYC Free Wi-Fi,LINK-010430,2017-09-25T00:00:00.000,4,Queens,QN28,Jackson Heights,25.00000000000,11372,403.00000000000,283.00000000000,283.00000000000,4030000.00000000000,4012910050.00000000000,3884,\"(40.7475388201, -73.8854976102)\"\r\n9698,3,Limited Free,ALTICEUSA,Prospect Park,Skate Rental Area,40.65745199970,-73.96399099970,994240.97738100000,178805.93148000000,Outdoor,3 free 10 min sessions,Brooklyn,GuestWiFi,,9999-09-09T00:00:00.000,3,Brooklyn,BK99,park-cemetery-etc-Brooklyn,39.00000000000,11215,355.00000000000,177.00000000000,177.00000000000,3391508.00000000000,3011170001.00000000000,895,\"(40.6574519997, -73.9639909997)\"\r\n12663,1,Free,LinkNYC - Citybridge,mn-04-108485,705 8 AVENUE,40.75883097030,-73.98877954050,987358.47277400000,215739.49475200000,Outdoor Kiosk,\"Tablet Internet -phone , Free 1 GB Wi-FI Service\",New York,LinkNYC Free Wi-Fi,LINK-000528,2016-04-11T00:00:00.000,1,Manhattan,MN15,Clinton,3.00000000000,10036,104.00000000000,121.00000000000,121.00000000000,1024992.00000000000,1010350040.00000000000,3240,\"(40.7588309703, -73.9887795405)\"\r\n12593,3,Limited Free,ALTICEUSA,St. John's Recreation Center,DANCE ROOM,40.67375199970,-73.93489199950,1002310.30639000000,184749.13941000000,Indoor,3 free 10 min sessions,Brooklyn,GuestWiFi,,9999-09-09T00:00:00.000,3,Brooklyn,BK61,Crown Heights North,36.00000000000,11213,308.00000000000,345.00000000000,345.00000000000,3393257.00000000000,3013530001.00000000000,919,\"(40.6737519997, -73.9348919995)\"\r\n10355,1,Free,Fiberless,Governors Island,Building 403A Back,40.68919999960,-74.01696000010,979546.55532700000,190371.03564600000,Outdoor,Free - up to 5 mbs,New York,Governors Island,Governors Island Trust,9999-09-09T00:00:00.000,1,Manhattan,MN99,Governors Island,1.00000000000,10004,101.00000000000,5.00000000000,5.00000000000,1086358.00000000000,1000010010.00000000000,4948,\"(40.6891999996, -74.0169600001)\"\r\n11475,1,Free,LinkNYC - Citybridge,mn-05-122878,2 WEST 49 STREET,40.75795791210,-73.97792563040,990365.47824300000,215421.98259200000,Outdoor Kiosk,\"Tablet Internet -phone , Free 1 GB Wi-FI Service\",New York,LinkNYC Free Wi-Fi,LINK-013923,2017-10-20T00:00:00.000,1,Manhattan,MN17,Midtown-Midtown South,4.00000000000,10020,105.00000000000,96.00000000000,96.00000000000,1034508.00000000000,1012640040.00000000000,4370,\"(40.7579579121, -73.9779256304)\"\r\n10121,1,Free,Manhattan Down Alliance,36,\"74 Broadway, New York, NY 10006, USA\",40.70800019980,-74.01180270010,980977.73028600000,197220.27162000000,Outdoor,,New York,#DwtwnAllianceFreeWiFi,,9999-09-09T00:00:00.000,1,Manhattan,MN25,Battery Park City-Lower Manhattan,1.00000000000,10004,101.00000000000,7.00000000000,7.00000000000,1000815.00000000000,1000230007.00000000000,547,\"(40.7080001998, -74.0118027001)\"\r\n11096,2,Free,LinkNYC - Citybridge,bx-01-145854,217 EAST 138 STREET,40.81225338010,-73.92866452990,1003996.65078000000,235210.94465400000,Outdoor Kiosk,\"Tablet Internet -phone , Free 1 GB Wi-FI Service\",Bronx,LinkNYC Free Wi-Fi,LINK-018226,2017-10-19T00:00:00.000,2,Bronx,BX39,Mott Haven-Port Morris,8.00000000000,10451,201.00000000000,51.00000000000,51.00000000000,2000969.00000000000,2023400000.00000000000,4539,\"(40.8122533801, -73.9286645299)\"\r\n11043,2,Free,LinkNYC - Citybridge,bx-01-123208,2883 3 AVENUE,40.81669229970,-73.91671906940,1007301.78197000000,236831.11956300000,Outdoor Kiosk,\"Tablet Internet -phone , Free 1 GB Wi-FI Service\",Bronx,LinkNYC Free Wi-Fi,LINK-012921,2017-10-26T00:00:00.000,2,Bronx,BX34,Melrose South-Mott Haven North,17.00000000000,10455,201.00000000000,65.00000000000,65.00000000000,2001336.00000000000,2023740000.00000000000,4240,\"(40.8166922997, -73.9167190694)\"\r\n11022,1,Free,LinkNYC - Citybridge,mn-07-135898,609 COLUMBUS AVE,40.78883163020,-73.97033520010,992464.51997600000,226670.93187800000,Outdoor Kiosk,\"Tablet Internet -phone , Free 1 GB Wi-FI Service\",New York,LinkNYC Free Wi-Fi,LINK-012782,2018-05-21T00:00:00.000,1,Manhattan,MN12,Upper West Side,6.00000000000,10024,107.00000000000,173.00000000000,173.00000000000,1031543.00000000000,1012030000.00000000000,4219,\"(40.7888316302, -73.9703352001)\"\r\n11435,1,Free,LinkNYC - Citybridge,mn-03-139623,401 EAST 12 STREET,40.72996267770,-73.98328129630,988883.69249200000,205222.09715200000,Outdoor Kiosk,\"Tablet Internet -phone , Free 1 GB Wi-FI Service\",New York,LinkNYC Free Wi-Fi,LINK-010803,2018-02-15T00:00:00.000,1,Manhattan,MN22,East Village,2.00000000000,10009,103.00000000000,34.00000000000,34.00000000000,1083482.00000000000,1004400000.00000000000,3931,\"(40.7299626777, -73.9832812963)\"\r\n11453,1,Free,LinkNYC - Citybridge,mn-03-137963,122B ORCHARD ST,40.71950375970,-73.98947426960,987167.72938900000,201411.32294900000,Outdoor Kiosk,\"Tablet Internet -phone , Free 1 GB Wi-FI Service\",New York,LinkNYC Free Wi-Fi,LINK-010872,2016-12-28T00:00:00.000,1,Manhattan,MN27,Chinatown,1.00000000000,10002,103.00000000000,18.00000000000,18.00000000000,1005303.00000000000,1004100000.00000000000,3949,\"(40.7195037597, -73.9894742696)\"\r\n9969,2,Free,NYPL,Soundview,660 SOUNDVIEW AVENUE,40.81870935220,-73.86288995610,1022200.27514000000,237584.74699300000,Library,,Bronx,NYPL,,9999-09-09T00:00:00.000,2,Bronx,BX09,Soundview-Castle Hill-Clason Point-Harding Park,18.00000000000,10473,209.00000000000,20.00000000000,20.00000000000,2021838.00000000000,2035580014.00000000000,386,\"(40.8187093522, -73.8628899561)\"\r\n12127,1,Free,LinkNYC - Citybridge,mn-04-111683,101 West 14Th St,40.73756051040,-73.99684066050,985125.53071700000,207989.79962100000,Outdoor Kiosk,\"Tablet Internet -phone , Free 1 GB Wi-FI Service\",New York,LinkNYC Free Wi-Fi,LINK-000191,2016-12-02T00:00:00.000,1,Manhattan,MN13,Hudson Yards-Chelsea-Flatiron-Union Square,3.00000000000,10011,104.00000000000,81.00000000000,81.00000000000,1014526.00000000000,1007900030.00000000000,3082,\"(40.7375605104, -73.9968406605)\"\r\n",
  "_profiling_times": {
    "steps": {
      "1_load_data": 0.04461974976584315,
      "2_geo_batch_predict": 0.2878739172592759,
      "3_process_columns": 1.4674017499201,
      "4_latlong_pairing": 0.00012395810335874557,
      "5_spatial_coverage": 0.03689195867627859,
      "6_temporal_coverage": 0.015746917109936476,
      "sample_extraction": 0.0014162920415401459
    },
    "total": 4.609226250089705
  },
  "_wrapper_summary": {
    "changed_count": 9,
    "changes": [
      {
        "name": "y",
        "action": "set",
        "old_label": null,
        "new_label": "y_coord",
        "reason": "y_coord_xy_pair"
      },
      {
        "name": "city",
        "action": "set",
        "old_label": null,
        "new_label": "city",
        "reason": "city_name_and_values"
      },
      {
        "name": "boroname",
        "action": "set",
        "old_label": null,
        "new_label": "borough_code",
        "reason": "admin_name_and_values"
      },
      {
        "name": "ntacode",
        "action": "set",
        "old_label": null,
        "new_label": "borough_code",
        "reason": "admin_name_and_values"
      },
      {
        "name": "ntaname",
        "action": "set",
        "old_label": null,
        "new_label": "borough_code",
        "reason": "admin_name_and_values"
      },
      {
        "name": "coundist",
        "action": "set",
        "old_label": null,
        "new_label": "borough_code",
        "reason": "admin_name_and_values"
      },
      {
        "name": "zip",
        "action": "set",
        "old_label": null,
        "new_label": "zip5",
        "reason": "zip_name_and_pattern"
      },
      {
        "name": "borocd",
        "action": "set",
        "old_label": null,
        "new_label": "borough_code",
        "reason": "admin_name_and_values"
      },
      {
        "name": "location_lat_long",
        "action": "clear",
        "old_label": "longitude",
        "new_label": null,
        "reason": "clear_scalar_coord_on_pair_text"
      }
    ]
  },
  "dataset_name": "wifi_hotspots",
  "output_mode": "wrapped"
}